mail_service/__init__.py
mail_service/sendmail.py
mail_service-1.0.5.dist-info/LICENSE
mail_service-1.0.5.dist-info/METADATA
mail_service-1.0.5.dist-info/WHEEL
mail_service-1.0.5.dist-info/top_level.txt
mail_service-1.0.5.dist-info/RECORD
