Metadata-Version: 2.1
Name: mail-service
Version: 1.0.5
Summary: Sending email using various services.
Home-page: https://github.com/thaismtss/mail-service
Author: Thais Martins
Author-email: thaismartins1999@gmail.com
License: GNU AFFERO GENERAL PUBLIC LICENSE
Platform: UNKNOWN
Classifier: Development Status :: 1 - Planning
Classifier: Environment :: Console
Classifier: Intended Audience :: Developers
Classifier: License :: OSI Approved :: MIT License
Classifier: Natural Language :: Portuguese (Brazilian)
Classifier: Operating System :: Microsoft :: Windows :: Windows 10
Classifier: Programming Language :: Python :: 3.8
Classifier: Topic :: Communications :: Email
